{
    "name": "key-qwiickeypad",
    "version": "1.0.1",
    "description": "",
    "dependencies": {
        "core": "*"
    },
    "files": [
        "README.md",
        "main.blocks",
        "main.ts",
        "key-qwiickeypad.ts"
    ],
    "testFiles": [
        "test.ts"
    ],
    "public": true,
    "targetVersions": {
        "target": "4.0.29",
        "targetId": "calliopemini"
    },
    "supportedTargets": [
        "calliopemini",
        "microbit"
    ],
    "preferredEditor": "tsprj"
}
